vgd_counterfactuals/VERSION
vgd_counterfactuals/__init__.py
vgd_counterfactuals/base.py
vgd_counterfactuals/cli.py
vgd_counterfactuals/testing.py
vgd_counterfactuals/utils.py
vgd_counterfactuals/visualization.py
vgd_counterfactuals/examples/00_quickstart.py
vgd_counterfactuals/examples/01_visualization.py
vgd_counterfactuals/examples/README.rst
vgd_counterfactuals/examples/__init__.py
vgd_counterfactuals/experiments/README.rst
vgd_counterfactuals/experiments/template_experiment.py
vgd_counterfactuals/experiments/template_experiment_sub.py
vgd_counterfactuals/generate/__init__.py
vgd_counterfactuals/generate/colors.py
vgd_counterfactuals/generate/molecules.py
vgd_counterfactuals/generate/smiles_one_step_changes.py
vgd_counterfactuals/templates/article.tex.j2
vgd_counterfactuals-0.3.13.dist-info/METADATA
vgd_counterfactuals-0.3.13.dist-info/WHEEL
vgd_counterfactuals-0.3.13.dist-info/entry_points.txt
vgd_counterfactuals-0.3.13.dist-info/licenses/LICENSE
vgd_counterfactuals-0.3.13.dist-info/RECORD
