Metadata-Version: 2.4
Name: vgd_counterfactuals
Version: 0.3.13
Summary: Counterfactual explanations for GNNs based on the visual graph dataset format
Author-email: Jonas Teufel <jonseb1998@gmail.com>
Maintainer-email: Jonas Teufel <jonseb1998@gmail.com>
License: MIT license
License-File: LICENSE
Keywords: counterfactuals,explainable AI,graph neural networks
Classifier: Development Status :: 4 - Beta
Classifier: Intended Audience :: Developers
Classifier: License :: OSI Approved :: MIT License
Classifier: Programming Language :: Python :: 3.9
Classifier: Programming Language :: Python :: 3.10
Classifier: Programming Language :: Python :: 3.11
Classifier: Programming Language :: Python :: 3.12
Classifier: Topic :: Scientific/Engineering :: Artificial Intelligence
Requires-Python: <=3.12,>=3.9
Requires-Dist: click>=7.1.2
Requires-Dist: jinja2>=3.0.3
Requires-Dist: matplotlib>=3.5.3
Requires-Dist: numpy>=1.23.2
Requires-Dist: poetry-bumpversion>=0.3.0
Requires-Dist: pycomex>=0.9.2
Requires-Dist: python-decouple>=3.6
Requires-Dist: rdkit>=2022.9.5
Requires-Dist: visual-graph-datasets>=0.15.7
Provides-Extra: dev
Requires-Dist: mkdocs-material; extra == 'dev'
Requires-Dist: poetry-bumpversion>=0.3.0; extra == 'dev'
Requires-Dist: pytest>=7.1.3; extra == 'dev'
